{
  "schema_version": "1.2",
  "scenario": {
    "id": "CHILD_ERROR_LOOKS_AT_PARENT_03",
    "content_version": "2026-07-16.1-approved-v1",
    "sport": "football",
    "language": "ru",
    "title": "Ребёнок ошибается и смотрит на родителя",
    "short_title": "Реакция на ошибку",
    "stage": "during_match",
    "estimated_minutes": 8,
    "age_groups": [
      "6-8",
      "9-12",
      "13-16"
    ],
    "entry_node": "intro",
    "asset_manifest": "assets/asset_manifest.json",
    "nodes": {
      "intro": {
        "type": "info",
        "title": "Ситуация 3 из 7. Ребёнок ошибается и смотрит на родителя",
        "text_by_age": {
          "6-8": "Ребёнок делает неточную передачу и сразу смотрит на вас.",
          "9-12": "После ошибки ребёнка соперник создаёт опасный момент. Ребёнок на секунду отвлекается от игры и ищет вашу реакцию на трибуне.",
          "13-16": "После неудачного решения подросток на секунду переводит взгляд на вас, пытаясь понять вашу реакцию."
        },
        "next": "start_choice",
        "methodology": {
          "full_explanation": "Помочь родителю реагировать на ошибку ребёнка спокойно и предсказуемо.\n\nПосле неудачного игрового момента ребёнку важно:\n\n• не переключаться с игры на оценку родителя;\n• не зацикливаться на совершённой ошибке;\n• быстро замечать, что происходит на поле дальше;\n• продолжать самостоятельно принимать решения;\n• сохранять внимание к указаниям тренера."
        },
        "media": {
          "asset_id": "ui_dialogue_choice",
          "mode": "photo",
          "show_once_per_session": false,
          "presentation": "hero",
          "caption_strategy": "auto"
        }
      },
      "start_choice": {
        "type": "choice",
        "text_by_age": {
          "6-8": "Ребёнок ошибся и сразу посмотрел на вас. Как вы отреагируете?",
          "9-12": "После ошибки ребёнок ищет вашу реакцию на трибуне. Что вы сделаете?",
          "13-16": "Подросток после неудачного решения переводит взгляд на вас. Как вы отреагируете?"
        },
        "buttons": [
          {
            "id": "a",
            "label": "«Соберись! Что ты делаешь?»",
            "next": "a_choice",
            "tracking_code": "S03_A"
          },
          {
            "id": "b",
            "label": "«Ничего страшного! Продолжай».",
            "next": "b_choice",
            "tracking_code": "S03_B"
          },
          {
            "id": "c",
            "label": "Спокойно покажу: «Продолжай».",
            "next": "c_choice",
            "tracking_code": "S03_C"
          },
          {
            "id": "d",
            "label": "Подскажу, как нужно было сыграть.",
            "next": "d_choice",
            "tracking_code": "S03_D"
          }
        ]
      },
      "a_choice": {
        "type": "choice",
        "text": "Ребёнок возвращается в игру, но начинает действовать осторожнее. После следующего игрового момента он снова смотрит на вас.\n\nКак вы продолжите?",
        "buttons": [
          {
            "id": "a1",
            "label": "Только не ошибись ещё раз",
            "next": "a1_now",
            "tracking_code": "S03_A1"
          },
          {
            "id": "a2",
            "label": "Следующий игровой момент",
            "next": "a2_now",
            "tracking_code": "S03_A2"
          },
          {
            "id": "a3",
            "label": "Спокойно покажу: «Продолжай» — и перестану комментировать",
            "next": "a3_now",
            "tracking_code": "S03_A3"
          }
        ]
      },
      "a1_now": {
        "type": "outcome",
        "title": "Что может произойти сейчас",
        "text": "Внимание ребёнка переключается с игры на необходимость любой ценой избежать следующей ошибки.\n\nОн может начать действовать слишком осторожно и отказываться от решений, в которых есть риск.",
        "next": "a1_repeated"
      },
      "a1_repeated": {
        "type": "outcome",
        "title": "Если такая реакция повторяется",
        "text": "Ребёнок может реже проявлять инициативу и чаще проверять реакцию родителя после своих действий.",
        "next": "a1_advice"
      },
      "a1_advice": {
        "type": "advice",
        "title": "Практический совет",
        "text": "Не усиливайте страх новой ошибки. Помогите ребёнку оставить закончившийся момент позади и заметить, что происходит на поле сейчас.",
        "quote": "«Этот игровой момент закончился. Смотри, что происходит дальше».",
        "next": "summary_main",
        "media": {
          "asset_id": "ui_practice_task",
          "mode": "photo",
          "show_once_per_session": false,
          "presentation": "compact",
          "caption_strategy": "auto"
        }
      },
      "a2_now": {
        "type": "outcome",
        "title": "Что может произойти сейчас",
        "text": "Ошибка отделяется от продолжения игры. Ребёнок получает короткий сигнал вернуть внимание на поле.",
        "next": "a2_repeated"
      },
      "a2_repeated": {
        "type": "outcome",
        "title": "Если такая реакция повторяется",
        "text": "Ему может стать проще быстрее возвращаться в игру после неудачного действия.",
        "next": "a2_advice"
      },
      "a2_advice": {
        "type": "advice",
        "title": "Практический совет",
        "text": "Используйте короткую фразу без тактического разбора, оценки и напоминания о самой ошибке.",
        "quote": "«Следующий игровой момент».",
        "next": "summary_main",
        "media": {
          "asset_id": "ui_practice_task",
          "mode": "photo",
          "show_once_per_session": false,
          "presentation": "compact",
          "caption_strategy": "auto"
        }
      },
      "a3_now": {
        "type": "outcome",
        "title": "Что может произойти сейчас",
        "text": "Родитель прекращает резкую реакцию, а ребёнок получает нейтральный сигнал продолжить игру.",
        "next": "a3_repeated"
      },
      "a3_repeated": {
        "type": "outcome",
        "title": "Если такая реакция повторяется",
        "text": "Ребёнок может меньше зависеть от эмоциональной реакции трибуны и быстрее возвращать внимание на поле.",
        "next": "a3_advice"
      },
      "a3_advice": {
        "type": "advice",
        "title": "Практический совет",
        "text": "После матча можно признать, что первая реакция была слишком резкой. Это не ослабляет авторитет родителя, а показывает ребёнку пример исправления собственной ошибки.",
        "quote": "Во время игры:\n\n«Продолжай».\n\nПосле игры:\n\n«Я слишком резко отреагировал на твою ошибку. Мне стоило дать тебе спокойно продолжить игру».",
        "next": "summary_main",
        "media": {
          "asset_id": "ui_practice_task",
          "mode": "photo",
          "show_once_per_session": false,
          "presentation": "compact",
          "caption_strategy": "auto"
        }
      },
      "b_choice": {
        "type": "choice",
        "text": "Ребёнок продолжает играть. После следующей ошибки он снова ищет вашу реакцию.\n\nКак вы поступите?",
        "buttons": [
          {
            "id": "b1",
            "label": "Буду успокаивать после каждой ошибки",
            "next": "b1_now",
            "tracking_code": "S03_B1"
          },
          {
            "id": "b2",
            "label": "Добавлю: «Следующий игровой момент»",
            "next": "b2_now",
            "tracking_code": "S03_B2"
          },
          {
            "id": "b3",
            "label": "Использую заранее согласованный жест без слов",
            "next": "b3_now",
            "tracking_code": "S03_B3"
          }
        ]
      },
      "b1_now": {
        "type": "outcome",
        "title": "Что может произойти сейчас",
        "text": "Ребёнок получает поддержку, но одновременно начинает ждать подтверждения родителя после каждого неудачного действия.",
        "next": "b1_repeated"
      },
      "b1_repeated": {
        "type": "outcome",
        "title": "Если такая реакция повторяется",
        "text": "Ему может стать сложнее самостоятельно справляться с ошибками без постоянного сигнала с трибуны.",
        "next": "b1_advice"
      },
      "b1_advice": {
        "type": "advice",
        "title": "Практический совет",
        "text": "После одного спокойного сигнала дайте ребёнку пространство самому вернуться в игру. Не сопровождайте реакцией каждое его действие.",
        "quote": "«Продолжай игру».\n\nПосле этого лучше снова направить внимание на матч и не комментировать следующий момент.",
        "next": "summary_main",
        "media": {
          "asset_id": "ui_practice_task",
          "mode": "photo",
          "show_once_per_session": false,
          "presentation": "compact",
          "caption_strategy": "auto"
        }
      },
      "b2_now": {
        "type": "outcome",
        "title": "Что может произойти сейчас",
        "text": "Внимание ребёнка переключается с уже совершённой ошибки на происходящее сейчас.",
        "next": "b2_repeated"
      },
      "b2_repeated": {
        "type": "outcome",
        "title": "Если такая реакция повторяется",
        "text": "Ему может стать проще не задерживаться мысленно в прошлом игровом моменте.",
        "next": "b2_advice"
      },
      "b2_advice": {
        "type": "advice",
        "title": "Практический совет",
        "text": "Используйте одну и ту же короткую формулировку. Она должна возвращать внимание в игру, а не объяснять, как именно нужно действовать.",
        "quote": "«Следующий игровой момент».",
        "next": "summary_main",
        "media": {
          "asset_id": "ui_practice_task",
          "mode": "photo",
          "show_once_per_session": false,
          "presentation": "compact",
          "caption_strategy": "auto"
        }
      },
      "b3_now": {
        "type": "outcome",
        "title": "Что может произойти сейчас",
        "text": "Ребёнок получает знакомый сигнал без дополнительной речевой нагрузки и не отвлекается на длинную подсказку.",
        "next": "b3_repeated"
      },
      "b3_repeated": {
        "type": "outcome",
        "title": "Если такая реакция повторяется",
        "text": "Ему может стать проще самостоятельно возвращаться в игру после короткого взгляда на родителя.",
        "next": "b3_advice"
      },
      "b3_advice": {
        "type": "advice",
        "title": "Практический совет",
        "text": "Согласуйте жест заранее, до соревнования. Ребёнок должен точно понимать, что он означает только одно: «Продолжай играть».",
        "quote": "«Если после ошибки ты посмотришь на меня, я покажу тебе только один сигнал: продолжай играть».",
        "next": "summary_main",
        "media": {
          "asset_id": "ui_practice_task",
          "mode": "photo",
          "show_once_per_session": false,
          "presentation": "compact",
          "caption_strategy": "auto"
        }
      },
      "c_choice": {
        "type": "choice",
        "text": "Ребёнок сразу возвращает взгляд на поле и продолжает играть.\n\nЧто вы сделаете дальше?",
        "buttons": [
          {
            "id": "c1",
            "label": "При необходимости повторю тот же спокойный жест",
            "next": "c1_now",
            "tracking_code": "S03_C1"
          },
          {
            "id": "c2",
            "label": "После игры спрошу, что помогло вернуться",
            "next": "c2_now",
            "tracking_code": "S03_C2"
          },
          {
            "id": "c3",
            "label": "Скажу: «Вот, можешь же»",
            "next": "c3_now",
            "tracking_code": "S03_C3"
          }
        ]
      },
      "c1_now": {
        "type": "outcome",
        "title": "Что может произойти сейчас",
        "text": "Реакция родителя остаётся спокойной и предсказуемой. Ребёнку не приходится каждый раз угадывать, как взрослый оценил его действие.",
        "next": "c1_repeated"
      },
      "c1_repeated": {
        "type": "outcome",
        "title": "Если такая реакция повторяется",
        "text": "Взгляд на трибуну может становиться короче, а внимание ребёнка — быстрее возвращаться к игре.",
        "next": "c1_advice"
      },
      "c1_advice": {
        "type": "advice",
        "title": "Практический совет",
        "text": "Не превращайте жест в оценку каждого игрового момента. Используйте его только тогда, когда ребёнок действительно ищет вашу реакцию.",
        "quote": "«Во время игры я не буду оценивать каждый твой момент. Если ты посмотришь на меня, я покажу только: продолжай».",
        "next": "summary_main",
        "media": {
          "asset_id": "ui_practice_task",
          "mode": "photo",
          "show_once_per_session": false,
          "presentation": "compact",
          "caption_strategy": "auto"
        }
      },
      "c2_now": {
        "type": "outcome",
        "title": "Что может произойти сейчас",
        "text": "В центре разговора оказывается не сама ошибка, а то, как ребёнку удалось продолжить игру после неё.",
        "next": "c2_repeated"
      },
      "c2_repeated": {
        "type": "outcome",
        "title": "Если такая реакция повторяется",
        "text": "Ребёнок может постепенно замечать собственные способы восстановления и выбирать те, которые помогают именно ему.",
        "next": "c2_advice"
      },
      "c2_advice": {
        "type": "advice",
        "title": "Практический совет",
        "text": "Задайте вопрос после игры, когда ребёнок готов разговаривать. Не отвлекайте его от тренера во время перерыва и не требуйте немедленного ответа.",
        "quote": "«Что помогло тебе вернуться в игру после ошибки?»",
        "next": "summary_main",
        "media": {
          "asset_id": "ui_practice_task",
          "mode": "photo",
          "show_once_per_session": false,
          "presentation": "compact",
          "caption_strategy": "auto"
        }
      },
      "c3_now": {
        "type": "outcome",
        "title": "Что может произойти сейчас",
        "text": "Фраза звучит как похвала, но ребёнок может услышать в ней скрытое напоминание: до этого он играл недостаточно хорошо.",
        "next": "c3_repeated"
      },
      "c3_repeated": {
        "type": "outcome",
        "title": "Если такая реакция повторяется",
        "text": "Ошибка может начать связываться не с игровым решением, а с оценкой способностей или старания ребёнка.",
        "next": "c3_advice"
      },
      "c3_advice": {
        "type": "advice",
        "title": "Практический совет",
        "text": "Вместо общей оценки опишите конкретное действие, которое помогло ребёнку продолжить игру.",
        "quote": "«Ты быстро вернулся в игру после ошибки».",
        "next": "summary_main",
        "media": {
          "asset_id": "ui_practice_task",
          "mode": "photo",
          "show_once_per_session": false,
          "presentation": "compact",
          "caption_strategy": "auto"
        }
      },
      "d_choice": {
        "type": "choice",
        "text": "Вы жестами или словами пытаетесь объяснить ребёнку правильное решение. Он начинает переводить взгляд с поля на вас и обратно.\n\nКак вы продолжите?",
        "buttons": [
          {
            "id": "d1",
            "label": "Продолжу подсказывать, как играть",
            "next": "d1_now",
            "tracking_code": "S03_D1"
          },
          {
            "id": "d2",
            "label": "Остановлюсь и верну внимание ребёнка к тренеру",
            "next": "d2_now",
            "tracking_code": "S03_D2"
          },
          {
            "id": "d3",
            "label": "Предложу обсудить игровой момент после матча",
            "next": "d3_now",
            "tracking_code": "S03_D3"
          }
        ]
      },
      "d1_now": {
        "type": "outcome",
        "title": "Что может произойти сейчас",
        "text": "Внимание ребёнка делится между игрой, указаниями тренера и подсказками родителя.\n\nЕму становится сложнее следить за изменениями на поле и быстро принимать решения.",
        "next": "d1_repeated"
      },
      "d1_repeated": {
        "type": "outcome",
        "title": "Если такая реакция повторяется",
        "text": "Ребёнок может чаще ждать готовой подсказки с трибуны вместо самостоятельной оценки ситуации.",
        "next": "d1_advice"
      },
      "d1_advice": {
        "type": "advice",
        "title": "Практический совет",
        "text": "Тактические решения во время матча относятся к работе тренера и самого игрока. Родителю лучше не добавлять вторую систему указаний.",
        "quote": "«Слушай тренера и принимай решения сам».",
        "next": "summary_main",
        "media": {
          "asset_id": "ui_practice_task",
          "mode": "photo",
          "show_once_per_session": false,
          "presentation": "compact",
          "caption_strategy": "auto"
        }
      },
      "d2_now": {
        "type": "outcome",
        "title": "Что может произойти сейчас",
        "text": "Количество противоречащих друг другу подсказок уменьшается. Ребёнку становится понятнее, на чьи указания ориентироваться.",
        "next": "d2_repeated"
      },
      "d2_repeated": {
        "type": "outcome",
        "title": "Если такая реакция повторяется",
        "text": "Границы ролей могут стать яснее: тренер руководит игрой, ребёнок принимает решения, родитель поддерживает.",
        "next": "d2_advice"
      },
      "d2_advice": {
        "type": "advice",
        "title": "Практический совет",
        "text": "Спокойно прекратите вмешательство. Не сопровождайте это раздражением или демонстративным молчанием.",
        "quote": "«Слушай тренера. Я не буду добавлять свои указания».",
        "next": "summary_main",
        "media": {
          "asset_id": "ui_practice_task",
          "mode": "photo",
          "show_once_per_session": false,
          "presentation": "compact",
          "caption_strategy": "auto"
        }
      },
      "d3_now": {
        "type": "outcome",
        "title": "Что может произойти сейчас",
        "text": "Ребёнок получает возможность продолжить игру, а позже самостоятельно описать, что он видел и почему принял такое решение.",
        "next": "d3_repeated"
      },
      "d3_repeated": {
        "type": "outcome",
        "title": "Если такая реакция повторяется",
        "text": "Ему может стать проще анализировать собственные игровые решения, а не только ждать готового объяснения взрослого.",
        "next": "d3_advice"
      },
      "d3_advice": {
        "type": "advice",
        "title": "Практический совет",
        "text": "Сначала спросите, хочет ли ребёнок обсуждать этот момент. Возможно, он уже разобрал его с тренером или не готов возвращаться к нему сразу после матча.",
        "quote": "«Хочешь после игры обсудить этот момент или оставим его для разговора с тренером?»",
        "next": "summary_main",
        "media": {
          "asset_id": "ui_practice_task",
          "mode": "photo",
          "show_once_per_session": false,
          "presentation": "compact",
          "caption_strategy": "auto"
        }
      },
      "summary_main": {
        "type": "tool",
        "title": "Общий вывод",
        "text": "Когда ребёнок ошибается и смотрит на родителя, он может искать:\n\n• оценку своего действия;\n• подтверждение, что взрослый не сердится;\n• подсказку, как играть дальше;\n• помощь в переключении внимания;\n• привычную эмоциональную опору.\n\nРодителю не обязательно изображать восторг после каждой ошибки, давать тактический совет или постоянно успокаивать ребёнка.\n\nПолезнее сохранять спокойную и предсказуемую реакцию, которая сообщает:\n\nОшибка произошла. Игра продолжается. Смотри, что происходит дальше.\n\nЧем меньше ребёнку нужно расшифровывать эмоции родителя, тем легче ему сохранять внимание на поле и самостоятельно возвращаться в игру.",
        "next": "tool_01",
        "media": {
          "asset_id": "ui_insight",
          "mode": "photo",
          "show_once_per_session": false,
          "presentation": "card",
          "caption_strategy": "auto"
        }
      },
      "tool_01": {
        "type": "tool",
        "title": "Практический инструмент. Сигнал возвращения в игру",
        "text": "До матча договоритесь с ребёнком об одном коротком сигнале, который означает:\n\n«Ошибка закончилась. Продолжай играть».\n\nЭто может быть:\n\n• спокойный кивок;\n• открытая ладонь;\n• короткий жест рукой в сторону поля;\n• фраза «Продолжай»;\n• фраза «Следующий игровой момент».\n\nСигнал не должен:\n\n• подсказывать тактическое решение;\n• оценивать качество игры;\n• меняться в зависимости от серьёзности ошибки;\n• сопровождать каждое действие ребёнка;\n• заменять указания тренера.\n\nЭто не требование выполнять на поле одно действие. Задача сигнала — помочь ребёнку перестать смотреть на трибуну и снова сосредоточиться на игре.",
        "next": "tool_02",
        "media": {
          "asset_id": "ui_practice_task",
          "mode": "photo",
          "show_once_per_session": false,
          "presentation": "compact",
          "caption_strategy": "auto"
        }
      },
      "tool_02": {
        "type": "tool",
        "title": "Для детей 6–8 лет",
        "text": "Лучше использовать простой жест и короткое слово:\n\n«Продолжай».",
        "next": "tool_03",
        "media": {
          "asset_id": "ui_practice_task",
          "mode": "photo",
          "show_once_per_session": false,
          "presentation": "compact",
          "caption_strategy": "auto"
        }
      },
      "tool_03": {
        "type": "tool",
        "title": "Для детей 9–12 лет",
        "text": "Можно заранее договориться о жесте или фразе:\n\n«Следующий игровой момент».",
        "next": "tool_04",
        "media": {
          "asset_id": "ui_practice_task",
          "mode": "photo",
          "show_once_per_session": false,
          "presentation": "compact",
          "caption_strategy": "auto"
        }
      },
      "tool_04": {
        "type": "tool",
        "title": "Для подростков 13–16 лет",
        "text": "Сначала стоит спросить, нужен ли подростку вообще какой-либо видимый сигнал с трибуны. Для него чрезмерно заметная реакция родителя может быть не поддержкой, а дополнительным давлением.",
        "next": "completion",
        "media": {
          "asset_id": "ui_practice_task",
          "mode": "photo",
          "show_once_per_session": false,
          "presentation": "compact",
          "caption_strategy": "auto"
        }
      },
      "completion": {
        "type": "completion",
        "title": "Ситуация пройдена",
        "text": "Ситуация пройдена.\n\nВы увидели, как реакция родителя после ошибки может:\n\n• усилить страх новой ошибки;\n• создать зависимость от подтверждения с трибуны;\n• переключить внимание на тактические подсказки;\n• помочь ребёнку быстро вернуться в игру;\n• поддержать самостоятельный анализ после матча.\n\nЗаберите с собой правило:\n\nОдин спокойный сигнал — и внимание снова на игре.",
        "buttons": [
          {
            "id": "next",
            "label": "Перейти к ситуации 4",
            "next": "__NEXT_SCENARIO__"
          },
          {
            "id": "repeat",
            "label": "Повторить ситуацию",
            "next": "intro"
          },
          {
            "id": "home",
            "label": "Вернуться на главную",
            "next": "__MAIN_MENU__"
          }
        ],
        "media": {
          "asset_id": "ui_achievement",
          "mode": "photo",
          "show_once_per_session": false,
          "presentation": "hero",
          "caption_strategy": "auto"
        }
      }
    }
  }
}
